m3_rest_gar/__init__.py
m3_rest_gar/consts.py
m3_rest_gar/filters.py
m3_rest_gar/mixins.py
m3_rest_gar/serializers.py
m3_rest_gar/urls.py
m3_rest_gar/util.py
m3_rest_gar/views.py
m3_rest_gar-1.0.77784.dist-info/METADATA
m3_rest_gar-1.0.77784.dist-info/WHEEL
m3_rest_gar-1.0.77784.dist-info/top_level.txt
m3_rest_gar-1.0.77784.dist-info/RECORD
