Metadata-Version: 2.4
Name: m3-rest-gar
Version: 1.0.77784
Summary: REST-service for GAR.
Author: BARS Group
Author-email: bars@bars.group
License: MIT
Keywords: django rest gar
Classifier: Development Status :: 4 - Beta
Classifier: Environment :: Console
Classifier: Intended Audience :: Developers
Classifier: Natural Language :: Russian
Classifier: Natural Language :: English
Classifier: Programming Language :: Python :: 3.9
Classifier: Topic :: Software Development :: Libraries
Classifier: Topic :: Utilities
Requires-Dist: m3-gar>=1.1.2
Requires-Dist: Django==3.2.4
Requires-Dist: djangorestframework==3.12.4
Requires-Dist: django-oauth-toolkit==1.5.0
Requires-Dist: django-filter==2.4.0
Dynamic: author
Dynamic: author-email
Dynamic: classifier
Dynamic: description
Dynamic: keywords
Dynamic: license
Dynamic: requires-dist
Dynamic: summary
